{"v":"5.12.1","fr":30,"ip":0,"op":151,"w":1400,"h":3120,"nm":"Clear_LM_PhonePortrait","ddd":0,"assets":[{"id":"comp_0","nm":"Clear Large_VectorBlur","fr":30,"layers":[{"ddd":0,"ind":1,"ty":4,"nm":"polygon 18","sr":1,"ks":{"o":{"a":1,"k":[{"i":{"x":[0.667],"y":[1]},"o":{"x":[0.333],"y":[0]},"t":53.558,"s":[0]},{"i":{"x":[0.667],"y":[1]},"o":{"x":[0.333],"y":[0]},"t":77.27,"s":[100]},{"t":127,"s":[0]}],"ix":11},"r":{"a":0,"k":0,"ix":10},"p":{"a":0,"k":[2265.849,2447.642,0],"ix":2,"l":2},"a":{"a":0,"k":[-591.651,-852.858,0],"ix":1,"l":2},"s":{"a":0,"k":[28,28,100],"ix":6,"l":2}},"ao":0,"ef":[{"ty":29,"nm":"Gaussian Blur","np":5,"mn":"ADBE Gaussian Blur 2","ix":1,"en":1,"ef":[{"ty":0,"nm":"Blurriness","mn":"ADBE Gaussian Blur 2-0001","ix":1,"v":{"a":0,"k":20,"ix":1}},{"ty":7,"nm":"Blur Dimensions","mn":"ADBE Gaussian Blur 2-0002","ix":2,"v":{"a":0,"k":1,"ix":2}},{"ty":7,"nm":"Repeat Edge Pixels","mn":"ADBE Gaussian Blur 2-0003","ix":3,"v":{"a":0,"k":1,"ix":3}}]}],"shapes":[{"ty":"gr","it":[{"ty":"sr","sy":2,"d":1,"pt":{"a":0,"k":6,"ix":3},"p":{"a":0,"k":[0,0],"ix":4},"r":{"a":0,"k":15.947,"ix":5},"or":{"a":0,"k":328.685,"ix":7},"os":{"a":0,"k":0,"ix":9},"ix":1,"nm":"Polystar Path 1","mn":"ADBE Vector Shape - Star","hd":false},{"ty":"gf","o":{"a":0,"k":25,"ix":10},"r":1,"bm":0,"g":{"p":3,"k":{"a":0,"k":[0,1,1,1,0.5,1,1,1,1,1,1,1,0.155,1,0.578,0.5,1,0],"ix":9}},"s":{"a":0,"k":[61.192,-82.488],"ix":5},"e":{"a":0,"k":[-85.493,302.552],"ix":6},"t":2,"h":{"a":0,"k":0,"ix":7},"a":{"a":0,"k":0,"ix":8},"nm":"Gradient Fill 1","mn":"ADBE Vector Graphic - G-Fill","hd":false},{"ty":"tr","p":{"a":0,"k":[-591.651,-852.858],"ix":2},"a":{"a":0,"k":[0,0],"ix":1},"s":{"a":0,"k":[100,100],"ix":3},"r":{"a":0,"k":0,"ix":6},"o":{"a":0,"k":100,"ix":7},"sk":{"a":0,"k":0,"ix":4},"sa":{"a":0,"k":0,"ix":5},"nm":"Transform"}],"nm":"Polystar 1","np":2,"cix":2,"bm":0,"ix":1,"mn":"ADBE Vector Group","hd":false}],"ip":53.5576171875,"op":128,"st":0,"ct":1,"bm":0},{"ddd":0,"ind":2,"ty":4,"nm":"polygon 17","sr":1,"ks":{"o":{"a":1,"k":[{"i":{"x":[1],"y":[1]},"o":{"x":[0.167],"y":[0.167]},"t":17.798,"s":[0]},{"t":51.707,"s":[70],"h":1},{"i":{"x":[0.833],"y":[0.833]},"o":{"x":[0.167],"y":[0.167]},"t":60.632,"s":[70]},{"i":{"x":[0.795],"y":[0.383]},"o":{"x":[0.164],"y":[0.718]},"t":78.479,"s":[100]},{"t":118,"s":[0]}],"ix":11},"r":{"a":0,"k":0,"ix":10},"p":{"a":0,"k":[1803.849,1989.642,0],"ix":2,"l":2},"a":{"a":0,"k":[-591.651,-852.858,0],"ix":1,"l":2},"s":{"a":0,"k":[100,100,100],"ix":6,"l":2}},"ao":0,"ef":[{"ty":29,"nm":"Gaussian Blur","np":5,"mn":"ADBE Gaussian Blur 2","ix":1,"en":1,"ef":[{"ty":0,"nm":"Blurriness","mn":"ADBE Gaussian Blur 2-0001","ix":1,"v":{"a":0,"k":20,"ix":1}},{"ty":7,"nm":"Blur Dimensions","mn":"ADBE Gaussian Blur 2-0002","ix":2,"v":{"a":0,"k":1,"ix":2}},{"ty":7,"nm":"Repeat Edge Pixels","mn":"ADBE Gaussian Blur 2-0003","ix":3,"v":{"a":0,"k":1,"ix":3}}]}],"shapes":[{"ty":"gr","it":[{"ty":"sr","sy":2,"d":1,"pt":{"a":0,"k":6,"ix":3},"p":{"a":0,"k":[0,0],"ix":4},"r":{"a":0,"k":15.947,"ix":5},"or":{"a":0,"k":328.685,"ix":7},"os":{"a":0,"k":0,"ix":9},"ix":1,"nm":"Polystar Path 1","mn":"ADBE Vector Shape - Star","hd":false},{"ty":"gf","o":{"a":0,"k":25,"ix":10},"r":1,"bm":0,"g":{"p":3,"k":{"a":0,"k":[0,1,1,1,0.5,1,1,1,1,1,1,1,0.155,1,0.578,0.5,1,0],"ix":9}},"s":{"a":0,"k":[61.192,-82.488],"ix":5},"e":{"a":0,"k":[-85.493,302.552],"ix":6},"t":2,"h":{"a":0,"k":0,"ix":7},"a":{"a":0,"k":0,"ix":8},"nm":"Gradient Fill 1","mn":"ADBE Vector Graphic - G-Fill","hd":false},{"ty":"tr","p":{"a":0,"k":[-591.651,-852.858],"ix":2},"a":{"a":0,"k":[0,0],"ix":1},"s":{"a":0,"k":[100,100],"ix":3},"r":{"a":0,"k":0,"ix":6},"o":{"a":0,"k":100,"ix":7},"sk":{"a":0,"k":0,"ix":4},"sa":{"a":0,"k":0,"ix":5},"nm":"Transform"}],"nm":"Polystar 1","np":2,"cix":2,"bm":0,"ix":1,"mn":"ADBE Vector Group","hd":false}],"ip":17.7978515625,"op":119,"st":0,"ct":1,"bm":0},{"ddd":0,"ind":3,"ty":4,"nm":"sun circle flare 1","sr":1,"ks":{"o":{"a":1,"k":[{"i":{"x":[0.833],"y":[0.833]},"o":{"x":[0.167],"y":[0.167]},"t":0,"s":[55]},{"i":{"x":[0.833],"y":[0.833]},"o":{"x":[0.167],"y":[0.167]},"t":75,"s":[100]},{"t":150,"s":[55]}],"ix":11},"r":{"a":0,"k":0,"ix":10},"p":{"a":0,"k":[3205.5,1726.5,0],"ix":2,"l":2},"a":{"a":0,"k":[1.925,-0.9,0],"ix":1,"l":2},"s":{"a":1,"k":[{"i":{"x":[0.667,0.667,0.667],"y":[1,1,1]},"o":{"x":[0.333,0.333,0.333],"y":[0,0,0]},"t":-35,"s":[115,115,100]},{"i":{"x":[0.667,0.667,0.667],"y":[1,1,1]},"o":{"x":[0.333,0.333,0.333],"y":[0,0,0]},"t":40,"s":[100,100,100]},{"i":{"x":[0.667,0.667,0.667],"y":[1,1,1]},"o":{"x":[0.333,0.333,0.333],"y":[0,0,0]},"t":115,"s":[115,115,100]},{"t":190,"s":[100,100,100]}],"ix":6,"l":2}},"ao":0,"ef":[{"ty":29,"nm":"Gaussian Blur","np":5,"mn":"ADBE Gaussian Blur 2","ix":1,"en":1,"ef":[{"ty":0,"nm":"Blurriness","mn":"ADBE Gaussian Blur 2-0001","ix":1,"v":{"a":0,"k":20,"ix":1}},{"ty":7,"nm":"Blur Dimensions","mn":"ADBE Gaussian Blur 2-0002","ix":2,"v":{"a":0,"k":1,"ix":2}},{"ty":7,"nm":"Repeat Edge Pixels","mn":"ADBE Gaussian Blur 2-0003","ix":3,"v":{"a":0,"k":1,"ix":3}}]}],"shapes":[{"ty":"gr","it":[{"d":1,"ty":"el","s":{"a":0,"k":[396.567,396.567],"ix":2},"p":{"a":0,"k":[0,0],"ix":3},"nm":"Ellipse Path 1","mn":"ADBE Vector Shape - Ellipse","hd":false},{"ty":"gf","o":{"a":0,"k":100,"ix":10},"r":1,"bm":0,"g":{"p":3,"k":{"a":0,"k":[0,1,1,1,0.5,1,1,1,1,1,1,1,0,1,0.5,0.625,1,0.25],"ix":9}},"s":{"a":0,"k":[1.307,2.03],"ix":5},"e":{"a":0,"k":[0.807,-200.191],"ix":6},"t":2,"h":{"a":0,"k":0,"ix":7},"a":{"a":0,"k":0,"ix":8},"nm":"Gradient Fill 1","mn":"ADBE Vector Graphic - G-Fill","hd":false},{"ty":"tr","p":{"a":0,"k":[1.925,-0.9],"ix":2},"a":{"a":0,"k":[0,0],"ix":1},"s":{"a":0,"k":[100,100],"ix":3},"r":{"a":0,"k":0,"ix":6},"o":{"a":0,"k":100,"ix":7},"sk":{"a":0,"k":0,"ix":4},"sa":{"a":0,"k":0,"ix":5},"nm":"Transform"}],"nm":"Ellipse 1","np":3,"cix":2,"bm":0,"ix":1,"mn":"ADBE Vector Group","hd":false}],"ip":0,"op":9999,"st":0,"ct":1,"bm":0},{"ddd":0,"ind":4,"ty":4,"nm":"sun circle flare 2","sr":1,"ks":{"o":{"a":1,"k":[{"i":{"x":[0.833],"y":[0.833]},"o":{"x":[0.167],"y":[0.167]},"t":-55,"s":[70]},{"i":{"x":[0.833],"y":[0.833]},"o":{"x":[0.167],"y":[0.017]},"t":20,"s":[45]},{"i":{"x":[0.833],"y":[0.833]},"o":{"x":[0.167],"y":[0.167]},"t":95,"s":[70]},{"t":170,"s":[45]}],"ix":11},"r":{"a":0,"k":0,"ix":10},"p":{"a":0,"k":[3205.5,1726.5,0],"ix":2,"l":2},"a":{"a":0,"k":[1.925,-0.9,0],"ix":1,"l":2},"s":{"a":1,"k":[{"i":{"x":[0.667,0.667,0.667],"y":[1,1,1]},"o":{"x":[0.333,0.333,0.333],"y":[0,0,0]},"t":-55,"s":[105,105,100]},{"i":{"x":[0.667,0.667,0.667],"y":[1,1,1]},"o":{"x":[0.333,0.333,0.333],"y":[0,0,0]},"t":20,"s":[100,100,100]},{"i":{"x":[0.667,0.667,0.667],"y":[1,1,1]},"o":{"x":[0.333,0.333,0.333],"y":[0,0,0]},"t":95,"s":[105,105,100]},{"t":170,"s":[100,100,100]}],"ix":6,"l":2}},"ao":0,"ef":[{"ty":29,"nm":"Gaussian Blur","np":5,"mn":"ADBE Gaussian Blur 2","ix":1,"en":1,"ef":[{"ty":0,"nm":"Blurriness","mn":"ADBE Gaussian Blur 2-0001","ix":1,"v":{"a":0,"k":20,"ix":1}},{"ty":7,"nm":"Blur Dimensions","mn":"ADBE Gaussian Blur 2-0002","ix":2,"v":{"a":0,"k":1,"ix":2}},{"ty":7,"nm":"Repeat Edge Pixels","mn":"ADBE Gaussian Blur 2-0003","ix":3,"v":{"a":0,"k":1,"ix":3}}]}],"shapes":[{"ty":"gr","it":[{"d":1,"ty":"el","s":{"a":0,"k":[1361.567,1361.567],"ix":2},"p":{"a":0,"k":[0,0],"ix":3},"nm":"Ellipse Path 1","mn":"ADBE Vector Shape - Ellipse","hd":false},{"ty":"gf","o":{"a":0,"k":100,"ix":10},"r":1,"bm":0,"g":{"p":3,"k":{"a":0,"k":[0,1,1,1,0.5,1,1,1,1,1,1,1,0.155,1,0.498,0.73,0.841,0.46,0.921,0.48,1,0.5],"ix":9}},"s":{"a":0,"k":[1.307,2.03],"ix":5},"e":{"a":0,"k":[0.459,-680.101],"ix":6},"t":2,"h":{"a":0,"k":0,"ix":7},"a":{"a":0,"k":0,"ix":8},"nm":"Gradient Fill 1","mn":"ADBE Vector Graphic - G-Fill","hd":false},{"ty":"tr","p":{"a":0,"k":[1.925,-0.9],"ix":2},"a":{"a":0,"k":[0,0],"ix":1},"s":{"a":0,"k":[100,100],"ix":3},"r":{"a":0,"k":0,"ix":6},"o":{"a":0,"k":100,"ix":7},"sk":{"a":0,"k":0,"ix":4},"sa":{"a":0,"k":0,"ix":5},"nm":"Transform"}],"nm":"Ellipse 1","np":3,"cix":2,"bm":0,"ix":1,"mn":"ADBE Vector Group","hd":false}],"ip":0,"op":9999,"st":0,"ct":1,"bm":0},{"ddd":0,"ind":5,"ty":4,"nm":"sun circle flare 3","sr":1,"ks":{"o":{"a":0,"k":26,"ix":11},"r":{"a":0,"k":0,"ix":10},"p":{"a":0,"k":[3205.5,1726.5,0],"ix":2,"l":2},"a":{"a":0,"k":[1.925,-0.9,0],"ix":1,"l":2},"s":{"a":1,"k":[{"i":{"x":[0.667,0.667,0.667],"y":[1,1,1]},"o":{"x":[0.333,0.333,0.333],"y":[0,0,0]},"t":-35,"s":[115,115,100]},{"i":{"x":[0.667,0.667,0.667],"y":[1,1,1]},"o":{"x":[0.333,0.333,0.333],"y":[0,0,0]},"t":40,"s":[100,100,100]},{"i":{"x":[0.667,0.667,0.667],"y":[1,1,1]},"o":{"x":[0.333,0.333,0.333],"y":[0,0,0]},"t":115,"s":[115,115,100]},{"t":190,"s":[100,100,100]}],"ix":6,"l":2}},"ao":0,"ef":[{"ty":29,"nm":"Gaussian Blur","np":5,"mn":"ADBE Gaussian Blur 2","ix":1,"en":1,"ef":[{"ty":0,"nm":"Blurriness","mn":"ADBE Gaussian Blur 2-0001","ix":1,"v":{"a":0,"k":20,"ix":1}},{"ty":7,"nm":"Blur Dimensions","mn":"ADBE Gaussian Blur 2-0002","ix":2,"v":{"a":0,"k":1,"ix":2}},{"ty":7,"nm":"Repeat Edge Pixels","mn":"ADBE Gaussian Blur 2-0003","ix":3,"v":{"a":0,"k":1,"ix":3}}]}],"shapes":[{"ty":"gr","it":[{"d":1,"ty":"el","s":{"a":0,"k":[1844.567,1844.567],"ix":2},"p":{"a":0,"k":[0,0],"ix":3},"nm":"Ellipse Path 1","mn":"ADBE Vector Shape - Ellipse","hd":false},{"ty":"gf","o":{"a":0,"k":100,"ix":10},"r":1,"bm":0,"g":{"p":3,"k":{"a":0,"k":[0,1,1,1,0.5,1,1,1,1,1,1,1,0.236,1,0.539,0.73,0.841,0.46,0.921,0.48,1,0.5],"ix":9}},"s":{"a":0,"k":[1.307,2.03],"ix":5},"e":{"a":0,"k":[-1.752,-918.319],"ix":6},"t":2,"h":{"a":0,"k":0,"ix":7},"a":{"a":0,"k":0,"ix":8},"nm":"Gradient Fill 1","mn":"ADBE Vector Graphic - G-Fill","hd":false},{"ty":"tr","p":{"a":0,"k":[1.925,-0.9],"ix":2},"a":{"a":0,"k":[0,0],"ix":1},"s":{"a":0,"k":[100,100],"ix":3},"r":{"a":0,"k":0,"ix":6},"o":{"a":0,"k":100,"ix":7},"sk":{"a":0,"k":0,"ix":4},"sa":{"a":0,"k":0,"ix":5},"nm":"Transform"}],"nm":"Ellipse 1","np":3,"cix":2,"bm":0,"ix":1,"mn":"ADBE Vector Group","hd":false}],"ip":0,"op":9999,"st":0,"ct":1,"bm":0},{"ddd":0,"ind":6,"ty":4,"nm":"Sun circle flare 4","sr":1,"ks":{"o":{"a":0,"k":15,"ix":11},"r":{"a":0,"k":0,"ix":10},"p":{"a":0,"k":[3205.5,1726.5,0],"ix":2,"l":2},"a":{"a":0,"k":[6,-6,0],"ix":1,"l":2},"s":{"a":1,"k":[{"i":{"x":[0.667,0.667,0.667],"y":[1,1,1]},"o":{"x":[0.333,0.333,0.333],"y":[0,0,0]},"t":-15,"s":[110,110,100]},{"i":{"x":[0.667,0.667,0.667],"y":[1,1,1]},"o":{"x":[0.333,0.333,0.333],"y":[0,0,0]},"t":60,"s":[100,100,100]},{"i":{"x":[0.667,0.667,0.667],"y":[1,1,1]},"o":{"x":[0.333,0.333,0.333],"y":[0,0,0]},"t":135,"s":[110,110,100]},{"t":210,"s":[100,100,100]}],"ix":6,"l":2}},"ao":0,"ef":[{"ty":29,"nm":"Gaussian Blur","np":5,"mn":"ADBE Gaussian Blur 2","ix":1,"en":1,"ef":[{"ty":0,"nm":"Blurriness","mn":"ADBE Gaussian Blur 2-0001","ix":1,"v":{"a":0,"k":20,"ix":1}},{"ty":7,"nm":"Blur Dimensions","mn":"ADBE Gaussian Blur 2-0002","ix":2,"v":{"a":0,"k":1,"ix":2}},{"ty":7,"nm":"Repeat Edge Pixels","mn":"ADBE Gaussian Blur 2-0003","ix":3,"v":{"a":0,"k":1,"ix":3}}]}],"shapes":[{"ty":"gr","it":[{"d":1,"ty":"el","s":{"a":0,"k":[2672.267,2672.267],"ix":2},"p":{"a":0,"k":[0,0],"ix":3},"nm":"Ellipse Path 1","mn":"ADBE Vector Shape - Ellipse","hd":false},{"ty":"st","c":{"a":0,"k":[1,1,1,1],"ix":3},"o":{"a":0,"k":100,"ix":4},"w":{"a":0,"k":21,"ix":5},"lc":1,"lj":1,"ml":4,"bm":0,"nm":"Stroke 1","mn":"ADBE Vector Graphic - Stroke","hd":false},{"ty":"tr","p":{"a":0,"k":[6,-6],"ix":2},"a":{"a":0,"k":[0,0],"ix":1},"s":{"a":0,"k":[100,100],"ix":3},"r":{"a":0,"k":0,"ix":6},"o":{"a":0,"k":100,"ix":7},"sk":{"a":0,"k":0,"ix":4},"sa":{"a":0,"k":0,"ix":5},"nm":"Transform"}],"nm":"Ellipse 1","np":3,"cix":2,"bm":0,"ix":1,"mn":"ADBE Vector Group","hd":false}],"ip":0,"op":9999,"st":0,"ct":1,"bm":0},{"ddd":0,"ind":7,"ty":4,"nm":"line 1","sr":1,"ks":{"o":{"a":1,"k":[{"i":{"x":[0.833],"y":[0.833]},"o":{"x":[0.167],"y":[0.167]},"t":-19,"s":[70]},{"i":{"x":[0.833],"y":[0.833]},"o":{"x":[0.167],"y":[0.167]},"t":19.934,"s":[60]},{"i":{"x":[0.833],"y":[0.833]},"o":{"x":[0.167],"y":[0.167]},"t":29.667,"s":[20]},{"i":{"x":[1],"y":[1]},"o":{"x":[0.167],"y":[0.167]},"t":34.533,"s":[100]},{"t":54,"s":[70],"h":1},{"i":{"x":[0.833],"y":[0.833]},"o":{"x":[0.167],"y":[0.167]},"t":58,"s":[70]},{"i":{"x":[0.833],"y":[0.833]},"o":{"x":[0.167],"y":[0.167]},"t":96.934,"s":[60]},{"i":{"x":[0.833],"y":[0.833]},"o":{"x":[0.167],"y":[0.167]},"t":106.667,"s":[20]},{"i":{"x":[0.629],"y":[0.939]},"o":{"x":[0.167],"y":[0.166]},"t":111.533,"s":[100]},{"i":{"x":[0.836],"y":[0.836]},"o":{"x":[0.206],"y":[0.206]},"t":131,"s":[69.743]},{"t":168.93359375,"s":[60]}],"ix":11},"r":{"a":0,"k":0,"ix":10},"p":{"a":0,"k":[2041.5,2962.5,0],"ix":2,"l":2},"a":{"a":0,"k":[1.5,0,0],"ix":1,"l":2},"s":{"a":0,"k":[158.262,167.087,100],"ix":6,"l":2}},"ao":0,"ef":[{"ty":29,"nm":"Gaussian Blur","np":5,"mn":"ADBE Gaussian Blur 2","ix":1,"en":1,"ef":[{"ty":0,"nm":"Blurriness","mn":"ADBE Gaussian Blur 2-0001","ix":1,"v":{"a":0,"k":20,"ix":1}},{"ty":7,"nm":"Blur Dimensions","mn":"ADBE Gaussian Blur 2-0002","ix":2,"v":{"a":0,"k":1,"ix":2}},{"ty":7,"nm":"Repeat Edge Pixels","mn":"ADBE Gaussian Blur 2-0003","ix":3,"v":{"a":0,"k":1,"ix":3}}]}],"shapes":[{"ty":"gr","it":[{"ind":0,"ty":"sh","ix":1,"ks":{"a":0,"k":{"i":[[0,0],[0,0]],"o":[[0,0],[0,0]],"v":[[-581,578],[636.022,-561.878]],"c":false},"ix":2},"nm":"Path 1","mn":"ADBE Vector Shape - Group","hd":false},{"ty":"gs","o":{"a":0,"k":40,"ix":9},"w":{"a":0,"k":33,"ix":10},"g":{"p":3,"k":{"a":0,"k":[0,1,1,1,0.5,1,1,1,1,1,1,1,0.121,1,0.413,0.575,0.704,0.15],"ix":8}},"s":{"a":0,"k":[-577.453,582.857],"ix":4},"e":{"a":0,"k":[575.536,-576.506],"ix":5},"t":1,"lc":2,"lj":1,"ml":4,"ml2":{"a":0,"k":4,"ix":13},"bm":0,"nm":"Gradient Stroke 1","mn":"ADBE Vector Graphic - G-Stroke","hd":false},{"ty":"tr","p":{"a":0,"k":[0,0],"ix":2},"a":{"a":0,"k":[0,0],"ix":1},"s":{"a":0,"k":[100,100],"ix":3},"r":{"a":0,"k":0,"ix":6},"o":{"a":0,"k":100,"ix":7},"sk":{"a":0,"k":0,"ix":4},"sa":{"a":0,"k":0,"ix":5},"nm":"Transform"}],"nm":"Shape 1","np":2,"cix":2,"bm":0,"ix":1,"mn":"ADBE Vector Group","hd":false}],"ip":0,"op":9999,"st":0,"ct":1,"bm":0},{"ddd":0,"ind":8,"ty":4,"nm":"line 2","sr":1,"ks":{"o":{"a":1,"k":[{"t":-39,"s":[85],"h":1},{"i":{"x":[0.833],"y":[1]},"o":{"x":[0.167],"y":[0]},"t":-35,"s":[85]},{"i":{"x":[0.833],"y":[0.833]},"o":{"x":[0.167],"y":[0.167]},"t":4,"s":[85]},{"i":{"x":[0.833],"y":[0.833]},"o":{"x":[0.167],"y":[0.167]},"t":14,"s":[100]},{"i":{"x":[0.764],"y":[0.764]},"o":{"x":[0.161],"y":[0.161]},"t":19,"s":[35]},{"i":{"x":[0.99],"y":[1]},"o":{"x":[0.167],"y":[0.167]},"t":37,"s":[82.368]},{"i":{"x":[0.833],"y":[1]},"o":{"x":[0.167],"y":[0]},"t":38,"s":[85]},{"i":{"x":[0.833],"y":[0.833]},"o":{"x":[0.167],"y":[0.167]},"t":77,"s":[85]},{"i":{"x":[0.833],"y":[0.833]},"o":{"x":[0.167],"y":[0.167]},"t":87,"s":[100]},{"i":{"x":[1],"y":[1]},"o":{"x":[0.167],"y":[0.167]},"t":92,"s":[35]},{"t":111,"s":[85],"h":1},{"i":{"x":[0.833],"y":[1]},"o":{"x":[0.167],"y":[0]},"t":115,"s":[85]},{"i":{"x":[0.833],"y":[0.833]},"o":{"x":[0.167],"y":[0.167]},"t":154,"s":[85]},{"i":{"x":[0.833],"y":[0.833]},"o":{"x":[0.167],"y":[0.167]},"t":164,"s":[100]},{"i":{"x":[0.833],"y":[0.833]},"o":{"x":[0.167],"y":[0.167]},"t":169,"s":[35]},{"t":188,"s":[85],"h":1}],"ix":11},"r":{"a":0,"k":-24.862,"ix":10},"p":{"a":0,"k":[2089.5,3850.5,0],"ix":2,"l":2},"a":{"a":0,"k":[1.5,0,0],"ix":1,"l":2},"s":{"a":0,"k":[125,125,100],"ix":6,"l":2}},"ao":0,"ef":[{"ty":29,"nm":"Gaussian Blur","np":5,"mn":"ADBE Gaussian Blur 2","ix":1,"en":1,"ef":[{"ty":0,"nm":"Blurriness","mn":"ADBE Gaussian Blur 2-0001","ix":1,"v":{"a":0,"k":20,"ix":1}},{"ty":7,"nm":"Blur Dimensions","mn":"ADBE Gaussian Blur 2-0002","ix":2,"v":{"a":0,"k":1,"ix":2}},{"ty":7,"nm":"Repeat Edge Pixels","mn":"ADBE Gaussian Blur 2-0003","ix":3,"v":{"a":0,"k":1,"ix":3}}]}],"shapes":[{"ty":"gr","it":[{"ind":0,"ty":"sh","ix":1,"ks":{"a":0,"k":{"i":[[0,0],[0,0]],"o":[[0,0],[0,0]],"v":[[-581,578],[728,-509]],"c":false},"ix":2},"nm":"Path 1","mn":"ADBE Vector Shape - Group","hd":false},{"ty":"gs","o":{"a":0,"k":16,"ix":9},"w":{"a":0,"k":33,"ix":10},"g":{"p":3,"k":{"a":0,"k":[0,1,1,1,0.5,1,1,1,1,1,1,1,0.121,1,0.561,0.5,1,0],"ix":8}},"s":{"a":0,"k":[-577.453,582.857],"ix":4},"e":{"a":0,"k":[575.536,-576.506],"ix":5},"t":1,"lc":2,"lj":1,"ml":4,"ml2":{"a":0,"k":4,"ix":13},"bm":0,"nm":"Gradient Stroke 1","mn":"ADBE Vector Graphic - G-Stroke","hd":false},{"ty":"tr","p":{"a":0,"k":[0,0],"ix":2},"a":{"a":0,"k":[0,0],"ix":1},"s":{"a":0,"k":[100,100],"ix":3},"r":{"a":0,"k":0,"ix":6},"o":{"a":0,"k":100,"ix":7},"sk":{"a":0,"k":0,"ix":4},"sa":{"a":0,"k":0,"ix":5},"nm":"Transform"}],"nm":"Shape 1","np":2,"cix":2,"bm":0,"ix":1,"mn":"ADBE Vector Group","hd":false}],"ip":0,"op":9999,"st":0,"ct":1,"bm":0},{"ddd":0,"ind":9,"ty":4,"nm":"line 2b","sr":1,"ks":{"o":{"a":1,"k":[{"i":{"x":[0.99],"y":[1]},"o":{"x":[0.167],"y":[0.167]},"t":0,"s":[35]},{"i":{"x":[0.833],"y":[1]},"o":{"x":[0.167],"y":[0]},"t":19,"s":[85]},{"i":{"x":[0.833],"y":[0.833]},"o":{"x":[0.167],"y":[0.167]},"t":58,"s":[85]},{"i":{"x":[0.833],"y":[0.833]},"o":{"x":[0.167],"y":[0.167]},"t":68,"s":[100]},{"i":{"x":[1],"y":[1]},"o":{"x":[0.167],"y":[0.167]},"t":73,"s":[35]},{"t":92,"s":[85],"h":1},{"i":{"x":[0.833],"y":[1]},"o":{"x":[0.167],"y":[0]},"t":96,"s":[85]},{"i":{"x":[0.833],"y":[0.833]},"o":{"x":[0.167],"y":[0.167]},"t":135,"s":[85]},{"i":{"x":[0.833],"y":[0.833]},"o":{"x":[0.167],"y":[0.167]},"t":145,"s":[100]},{"i":{"x":[0.833],"y":[0.833]},"o":{"x":[0.167],"y":[0.167]},"t":150,"s":[35]},{"t":169,"s":[85],"h":1}],"ix":11},"r":{"a":0,"k":0,"ix":10},"p":{"a":0,"k":[1685.5,2466.5,0],"ix":2,"l":2},"a":{"a":0,"k":[1.5,0,0],"ix":1,"l":2},"s":{"a":0,"k":[236.34,154.47,100],"ix":6,"l":2}},"ao":0,"ef":[{"ty":29,"nm":"Gaussian Blur","np":5,"mn":"ADBE Gaussian Blur 2","ix":1,"en":1,"ef":[{"ty":0,"nm":"Blurriness","mn":"ADBE Gaussian Blur 2-0001","ix":1,"v":{"a":0,"k":20,"ix":1}},{"ty":7,"nm":"Blur Dimensions","mn":"ADBE Gaussian Blur 2-0002","ix":2,"v":{"a":0,"k":1,"ix":2}},{"ty":7,"nm":"Repeat Edge Pixels","mn":"ADBE Gaussian Blur 2-0003","ix":3,"v":{"a":0,"k":1,"ix":3}}]}],"shapes":[{"ty":"gr","it":[{"ind":0,"ty":"sh","ix":1,"ks":{"a":0,"k":{"i":[[0,0],[0,0]],"o":[[0,0],[0,0]],"v":[[-581,578],[728,-509]],"c":false},"ix":2},"nm":"Path 1","mn":"ADBE Vector Shape - Group","hd":false},{"ty":"gs","o":{"a":0,"k":20,"ix":9},"w":{"a":0,"k":33,"ix":10},"g":{"p":3,"k":{"a":0,"k":[0,1,1,1,0.5,1,1,1,1,1,1,1,0.121,1,0.561,0.5,1,0],"ix":8}},"s":{"a":0,"k":[-577.453,582.857],"ix":4},"e":{"a":0,"k":[575.536,-576.506],"ix":5},"t":1,"lc":2,"lj":1,"ml":4,"ml2":{"a":0,"k":4,"ix":13},"bm":0,"nm":"Gradient Stroke 1","mn":"ADBE Vector Graphic - G-Stroke","hd":false},{"ty":"tr","p":{"a":0,"k":[0,0],"ix":2},"a":{"a":0,"k":[0,0],"ix":1},"s":{"a":0,"k":[100,100],"ix":3},"r":{"a":0,"k":0,"ix":6},"o":{"a":0,"k":100,"ix":7},"sk":{"a":0,"k":0,"ix":4},"sa":{"a":0,"k":0,"ix":5},"nm":"Transform"}],"nm":"Shape 1","np":2,"cix":2,"bm":0,"ix":1,"mn":"ADBE Vector Group","hd":false}],"ip":0,"op":9999,"st":0,"ct":1,"bm":0},{"ddd":0,"ind":10,"ty":4,"nm":"line 3","sr":1,"ks":{"o":{"a":1,"k":[{"i":{"x":[0.833],"y":[1]},"o":{"x":[0.167],"y":[0]},"t":-66,"s":[70]},{"i":{"x":[0.833],"y":[0.833]},"o":{"x":[0.167],"y":[0.167]},"t":-27,"s":[70]},{"i":{"x":[0.833],"y":[0.833]},"o":{"x":[0.167],"y":[0.167]},"t":-17,"s":[100]},{"i":{"x":[1],"y":[1]},"o":{"x":[0.167],"y":[0.167]},"t":-12,"s":[27]},{"t":7,"s":[70],"h":1},{"i":{"x":[0.833],"y":[1]},"o":{"x":[0.167],"y":[0]},"t":11,"s":[70]},{"i":{"x":[0.833],"y":[0.833]},"o":{"x":[0.167],"y":[0.167]},"t":50,"s":[70]},{"i":{"x":[0.833],"y":[0.833]},"o":{"x":[0.167],"y":[0.167]},"t":60,"s":[100]},{"i":{"x":[0.99],"y":[1]},"o":{"x":[0.161],"y":[0.153]},"t":65,"s":[27]},{"i":{"x":[0.731],"y":[0.391]},"o":{"x":[0.167],"y":[0]},"t":83,"s":[70]},{"t":84,"s":[70],"h":1},{"i":{"x":[0.833],"y":[0.833]},"o":{"x":[0.167],"y":[0.167]},"t":122,"s":[70]},{"i":{"x":[0.833],"y":[0.833]},"o":{"x":[0.167],"y":[0.167]},"t":132,"s":[100]},{"i":{"x":[1],"y":[1]},"o":{"x":[0.167],"y":[0.167]},"t":137,"s":[27]},{"t":156,"s":[70],"h":1},{"i":{"x":[0.833],"y":[1]},"o":{"x":[0.167],"y":[0]},"t":160,"s":[70]},{"i":{"x":[0.833],"y":[0.833]},"o":{"x":[0.167],"y":[0.167]},"t":199,"s":[70]},{"i":{"x":[0.833],"y":[0.833]},"o":{"x":[0.167],"y":[0.167]},"t":209,"s":[100]},{"i":{"x":[0.833],"y":[0.833]},"o":{"x":[0.167],"y":[0.167]},"t":214,"s":[27]},{"t":233,"s":[70],"h":1}],"ix":11},"r":{"a":0,"k":-24.862,"ix":10},"p":{"a":0,"k":[1639.5,2002.5,0],"ix":2,"l":2},"a":{"a":0,"k":[1.5,0,0],"ix":1,"l":2},"s":{"a":0,"k":[100,100,100],"ix":6,"l":2}},"ao":0,"ef":[{"ty":29,"nm":"Gaussian Blur","np":5,"mn":"ADBE Gaussian Blur 2","ix":1,"en":1,"ef":[{"ty":0,"nm":"Blurriness","mn":"ADBE Gaussian Blur 2-0001","ix":1,"v":{"a":0,"k":20,"ix":1}},{"ty":7,"nm":"Blur Dimensions","mn":"ADBE Gaussian Blur 2-0002","ix":2,"v":{"a":0,"k":1,"ix":2}},{"ty":7,"nm":"Repeat Edge Pixels","mn":"ADBE Gaussian Blur 2-0003","ix":3,"v":{"a":0,"k":1,"ix":3}}]}],"shapes":[{"ty":"gr","it":[{"ind":0,"ty":"sh","ix":1,"ks":{"a":0,"k":{"i":[[0,0],[0,0]],"o":[[0,0],[0,0]],"v":[[-1380.656,-374.475],[1227.089,326.242]],"c":false},"ix":2},"nm":"Path 1","mn":"ADBE Vector Shape - Group","hd":false},{"ty":"gs","o":{"a":0,"k":16,"ix":9},"w":{"a":0,"k":33,"ix":10},"g":{"p":3,"k":{"a":0,"k":[0,1,1,1,0.5,1,1,1,1,1,1,1,0.121,1,0.561,0.5,1,0],"ix":8}},"s":{"a":0,"k":[-1380.611,-378.176],"ix":4},"e":{"a":0,"k":[1236.112,332.485],"ix":5},"t":1,"lc":2,"lj":1,"ml":4,"ml2":{"a":0,"k":4,"ix":13},"bm":0,"nm":"Gradient Stroke 1","mn":"ADBE Vector Graphic - G-Stroke","hd":false},{"ty":"tr","p":{"a":0,"k":[0,0],"ix":2},"a":{"a":0,"k":[0,0],"ix":1},"s":{"a":0,"k":[100,100],"ix":3},"r":{"a":0,"k":0,"ix":6},"o":{"a":0,"k":100,"ix":7},"sk":{"a":0,"k":0,"ix":4},"sa":{"a":0,"k":0,"ix":5},"nm":"Transform"}],"nm":"Shape 1","np":2,"cix":2,"bm":0,"ix":1,"mn":"ADBE Vector Group","hd":false}],"ip":0,"op":9999,"st":0,"ct":1,"bm":0},{"ddd":0,"ind":11,"ty":4,"nm":"line 4","sr":1,"ks":{"o":{"a":1,"k":[{"i":{"x":[0.833],"y":[0.833]},"o":{"x":[0.167],"y":[0.167]},"t":-4,"s":[70]},{"i":{"x":[0.833],"y":[0.833]},"o":{"x":[0.167],"y":[0.167]},"t":6,"s":[17]},{"i":{"x":[0.833],"y":[0.833]},"o":{"x":[0.167],"y":[0.167]},"t":11,"s":[100]},{"t":30,"s":[70],"h":1},{"i":{"x":[0.833],"y":[0.833]},"o":{"x":[0.167],"y":[0.167]},"t":69,"s":[70]},{"i":{"x":[0.833],"y":[0.833]},"o":{"x":[0.167],"y":[0.167]},"t":79,"s":[17]},{"i":{"x":[1],"y":[1]},"o":{"x":[0.167],"y":[0.167]},"t":84,"s":[100]},{"t":103,"s":[70],"h":1},{"i":{"x":[0.833],"y":[1]},"o":{"x":[0.167],"y":[0]},"t":107,"s":[70]},{"i":{"x":[0.833],"y":[0.833]},"o":{"x":[0.167],"y":[0.167]},"t":146,"s":[70]},{"i":{"x":[0.833],"y":[0.833]},"o":{"x":[0.167],"y":[0.167]},"t":156,"s":[17]},{"i":{"x":[0.833],"y":[0.833]},"o":{"x":[0.167],"y":[0.167]},"t":161,"s":[100]},{"t":180,"s":[70],"h":1}],"ix":11},"r":{"a":0,"k":0,"ix":10},"p":{"a":0,"k":[2997.5,4064.5,0],"ix":2,"l":2},"a":{"a":0,"k":[-752.004,-1266.141,0],"ix":1,"l":2},"s":{"a":0,"k":[125,125,100],"ix":6,"l":2}},"ao":0,"ef":[{"ty":29,"nm":"Gaussian Blur","np":5,"mn":"ADBE Gaussian Blur 2","ix":1,"en":1,"ef":[{"ty":0,"nm":"Blurriness","mn":"ADBE Gaussian Blur 2-0001","ix":1,"v":{"a":0,"k":20,"ix":1}},{"ty":7,"nm":"Blur Dimensions","mn":"ADBE Gaussian Blur 2-0002","ix":2,"v":{"a":0,"k":1,"ix":2}},{"ty":7,"nm":"Repeat Edge Pixels","mn":"ADBE Gaussian Blur 2-0003","ix":3,"v":{"a":0,"k":1,"ix":3}}]}],"shapes":[{"ty":"gr","it":[{"ind":0,"ty":"sh","ix":1,"ks":{"a":0,"k":{"i":[[0,0],[0,0]],"o":[[0,0],[0,0]],"v":[[-948.656,-194.476],[-579.702,-2885.067]],"c":false},"ix":2},"nm":"Path 1","mn":"ADBE Vector Shape - Group","hd":false},{"ty":"gs","o":{"a":0,"k":30,"ix":9},"w":{"a":0,"k":33,"ix":10},"g":{"p":3,"k":{"a":0,"k":[0,1,1,1,0.5,1,1,1,1,1,1,1,0.121,1,0.561,0.5,1,0],"ix":8}},"s":{"a":0,"k":[-936.659,-200.012],"ix":4},"e":{"a":0,"k":[-572.214,-2884.665],"ix":5},"t":1,"lc":2,"lj":1,"ml":4,"ml2":{"a":0,"k":4,"ix":13},"bm":0,"nm":"Gradient Stroke 1","mn":"ADBE Vector Graphic - G-Stroke","hd":false},{"ty":"tr","p":{"a":0,"k":[0,0],"ix":2},"a":{"a":0,"k":[0,0],"ix":1},"s":{"a":0,"k":[100,100],"ix":3},"r":{"a":0,"k":0,"ix":6},"o":{"a":0,"k":100,"ix":7},"sk":{"a":0,"k":0,"ix":4},"sa":{"a":0,"k":0,"ix":5},"nm":"Transform"}],"nm":"Shape 1","np":2,"cix":2,"bm":0,"ix":1,"mn":"ADBE Vector Group","hd":false}],"ip":0,"op":9999,"st":0,"ct":1,"bm":0}]}],"layers":[{"ddd":0,"ind":1,"ty":0,"nm":"Clear Phone P","refId":"comp_0","sr":1,"ks":{"o":{"a":0,"k":100,"ix":11},"r":{"a":0,"k":0,"ix":10},"p":{"a":0,"k":[612,1560,0],"ix":2,"l":2},"a":{"a":0,"k":[2395.5,2842.5,0],"ix":1,"l":2},"s":{"a":0,"k":[100,100,100],"ix":6,"l":2}},"ao":0,"w":4791,"h":5685,"ip":0,"op":300,"st":0,"bm":0}],"markers":[],"props":{}}